guardbench/__init__.py
guardbench/analyze.py
guardbench/evaluate.py
guardbench/paths.py
guardbench/report.py
guardbench/utils.py
guardbench/benchmark/__init__.py
guardbench/benchmark/effectiveness.py
guardbench/benchmark/efficiency.py
guardbench/datasets/__init__.py
guardbench/datasets/aart.py
guardbench/datasets/advbench_behaviors.py
guardbench/datasets/advbench_strings.py
guardbench/datasets/beaver_tails_330k.py
guardbench/datasets/bibtex.py
guardbench/datasets/bot_adversarial_dialogue.py
guardbench/datasets/cat_qa.py
guardbench/datasets/convabuse.py
guardbench/datasets/custom_dataset.py
guardbench/datasets/dataset.py
guardbench/datasets/decoding_trust_stereotypes.py
guardbench/datasets/dices_350.py
guardbench/datasets/dices_990.py
guardbench/datasets/do_anything_now_questions.py
guardbench/datasets/do_not_answer.py
guardbench/datasets/dynahate.py
guardbench/datasets/harm_eval.py
guardbench/datasets/harmbench_behaviors.py
guardbench/datasets/harmful_q.py
guardbench/datasets/harmful_qa.py
guardbench/datasets/harmful_qa_questions.py
guardbench/datasets/hatecheck.py
guardbench/datasets/hatemoji_check.py
guardbench/datasets/hex_phi.py
guardbench/datasets/i_cona.py
guardbench/datasets/i_controversial.py
guardbench/datasets/i_malicious_instructions.py
guardbench/datasets/i_physical_safety.py
guardbench/datasets/jbb_behaviors.py
guardbench/datasets/malicious_instruct.py
guardbench/datasets/mitre.py
guardbench/datasets/niche_hazard_qa.py
guardbench/datasets/openai_moderation_dataset.py
guardbench/datasets/prosocial_dialog.py
guardbench/datasets/safe_text.py
guardbench/datasets/simple_safety_tests.py
guardbench/datasets/strong_reject_instructions.py
guardbench/datasets/tdc_red_teaming.py
guardbench/datasets/tech_hazard_qa.py
guardbench/datasets/toxic_chat.py
guardbench/datasets/toxigen.py
guardbench/datasets/xstest.py
guardbench-1.0.1.dist-info/LICENSE.txt
guardbench-1.0.1.dist-info/METADATA
guardbench-1.0.1.dist-info/NOTICE.txt
guardbench-1.0.1.dist-info/WHEEL
guardbench-1.0.1.dist-info/top_level.txt
guardbench-1.0.1.dist-info/RECORD
