Metadata-Version: 2.1
Name: guardbench
Version: 1.0.1
Summary: GuardBench: A Large-Scale Benchmark for Guardrail Models
Home-page: 
Author: Elias Bassani
Author-email: elias.bassani@ec.europa.eu
Keywords: harmful content detection,harmful content,toxic content detection,toxic content,guardrails,guardrail models,guardrail models evaluation,guardrail models benchmark,evaluation,benchmark
Classifier: Programming Language :: Python :: 3
Classifier: License :: OSI Approved :: MIT License
Classifier: Intended Audience :: Science/Research
Classifier: Operating System :: OS Independent
Classifier: Topic :: Text Processing :: General
Requires-Python: >=3.10
License-File: LICENSE.txt
License-File: NOTICE.txt
Requires-Dist: datasets
Requires-Dist: huggingface-hub
Requires-Dist: imbalanced-learn
Requires-Dist: ipython
Requires-Dist: loguru
Requires-Dist: scikit-learn
Requires-Dist: tabulate
Requires-Dist: tqdm
Requires-Dist: unified-io
